LICENSE
MANIFEST.in
setup.py
tap_mysql/__init__.py
tap_mysql/connection.py
tap_mysql.egg-info/PKG-INFO
tap_mysql.egg-info/SOURCES.txt
tap_mysql.egg-info/dependency_links.txt
tap_mysql.egg-info/entry_points.txt
tap_mysql.egg-info/requires.txt
tap_mysql.egg-info/top_level.txt
tap_mysql/sync_strategies/__init__.py
tap_mysql/sync_strategies/binlog.py
tap_mysql/sync_strategies/common.py
tap_mysql/sync_strategies/full_table.py
tap_mysql/sync_strategies/incremental.py