Metadata-Version: 1.1
Name: tap-mysql
Version: 1.15.0
Summary: Singer.io tap for extracting data from MySQL
Home-page: https://singer.io
Author: Stitch
Author-email: UNKNOWN
License: UNKNOWN
Platform: UNKNOWN
Classifier: Programming Language :: Python :: 3 :: Only
